sunra_apispec/__init__.py
sunra_apispec/model_mapping.py
sunra_apispec/model_registry.py
sunra_apispec/base/__init__.py
sunra_apispec/base/adapter_interface.py
sunra_apispec/base/base_api_service.py
sunra_apispec/base/common.py
sunra_apispec/base/output_schema.py
sunra_apispec/base/utils.py
sunra_apispec/specs/__init__.py
sunra_apispec/specs/ace_step/__init__.py
sunra_apispec/specs/ace_step/v1_3_5b/__init__.py
sunra_apispec/specs/ace_step/v1_3_5b/endpoints.py
sunra_apispec/specs/ace_step/v1_3_5b/sunra_schema.py
sunra_apispec/specs/ace_step/v1_3_5b/service_providers/__init__.py
sunra_apispec/specs/ace_step/v1_3_5b/service_providers/fal/__init__.py
sunra_apispec/specs/ace_step/v1_3_5b/service_providers/fal/adapter.py
sunra_apispec/specs/ace_step/v1_3_5b/service_providers/fal/schema.py
sunra_apispec/specs/black_forest_labs/__init__.py
sunra_apispec/specs/black_forest_labs/flux_1_1_pro/__init__.py
sunra_apispec/specs/black_forest_labs/flux_1_1_pro/endpoints.py
sunra_apispec/specs/black_forest_labs/flux_1_1_pro/sunra_schema.py
sunra_apispec/specs/black_forest_labs/flux_1_1_pro/service_providers/__init__.py
sunra_apispec/specs/black_forest_labs/flux_1_1_pro/service_providers/bfl_official/__init__.py
sunra_apispec/specs/black_forest_labs/flux_1_1_pro/service_providers/bfl_official/adapter.py
sunra_apispec/specs/black_forest_labs/flux_1_1_pro/service_providers/bfl_official/schema.py
sunra_apispec/specs/black_forest_labs/flux_1_1_pro/service_providers/littercoder/__init__.py
sunra_apispec/specs/black_forest_labs/flux_1_1_pro/service_providers/littercoder/adapter.py
sunra_apispec/specs/black_forest_labs/flux_1_1_pro/service_providers/littercoder/schema.py
sunra_apispec/specs/black_forest_labs/flux_1_1_pro_ultra/__init__.py
sunra_apispec/specs/black_forest_labs/flux_1_1_pro_ultra/endpoints.py
sunra_apispec/specs/black_forest_labs/flux_1_1_pro_ultra/sunra_schema.py
sunra_apispec/specs/black_forest_labs/flux_1_1_pro_ultra/service_providers/__init__.py
sunra_apispec-0.0.11.dist-info/LICENSE
sunra_apispec-0.0.11.dist-info/METADATA
sunra_apispec-0.0.11.dist-info/WHEEL
sunra_apispec-0.0.11.dist-info/top_level.txt
sunra_apispec-0.0.11.dist-info/RECORD
