Metadata-Version: 2.1
Name: sunra-apispec
Version: 0.0.11
Summary: A toolkit for managing and generating API specifications for various AI services
Home-page: https://github.com/sunra-ai/APISpecToolkit
Author: sunra.ai
Author-email: admin@sunra.ai
Classifier: Programming Language :: Python :: 3
Classifier: License :: OSI Approved :: MIT License
Classifier: Operating System :: OS Independent
Requires-Python: >=3.8
License-File: LICENSE
Requires-Dist: pydantic
Requires-Dist: fastapi
Requires-Dist: requests
Requires-Dist: tiktoken
